lino_prima/__init__.py
lino_prima/lib/__init__.py
lino_prima/lib/cert/__init__.py
lino_prima/lib/cert/mixins.py
lino_prima/lib/cert/models.py
lino_prima/lib/cert/ui.py
lino_prima/lib/cert/config/cert/Certificate/default.weasy.html
lino_prima/lib/prima/__init__.py
lino_prima/lib/prima/help_texts.py
lino_prima/lib/prima/migrate.py
lino_prima/lib/prima/models.py
lino_prima/lib/prima/settings.py
lino_prima/lib/prima/user_types.py
lino_prima/lib/prima/fixtures/csv2db.py
lino_prima/lib/prima/fixtures/demo.py
lino_prima/lib/prima/locale/django.pot
lino_prima/lib/prima/locale/de/LC_MESSAGES/django.mo
lino_prima/lib/prima/locale/de/LC_MESSAGES/django.po
lino_prima/lib/prima/locale/et/LC_MESSAGES/django.po
lino_prima/lib/prima/locale/fr/LC_MESSAGES/django.po
lino_prima/lib/projects/__init__.py
lino_prima/lib/projects/choicelists.py
lino_prima/lib/projects/models.py
lino_prima/lib/projects/ui.py
lino_prima/lib/projects/config/ratings/Project/default.weasy.html
lino_prima/lib/ratings/__init__.py
lino_prima/lib/ratings/choicelists.py
lino_prima/lib/ratings/mixins.py
lino_prima/lib/ratings/models.py
lino_prima/lib/ratings/ui.py
lino_prima/lib/ratings/utils.py
lino_prima/lib/school/__init__.py
lino_prima/lib/school/mixins.py
lino_prima/lib/school/models.py
lino_prima/lib/school/roles.py
lino_prima/lib/school/ui.py
lino_prima/lib/users/__init__.py
lino_prima/lib/users/models.py
lino_prima/lib/users/ui.py
lino_prima/lib/users/fixtures/__init__.py
lino_prima/lib/users/fixtures/demo.py
lino_prima/lib/users/fixtures/demo2.py
lino_prima/lib/users/fixtures/demo_users.py
lino_prima/projects/__init__.py
lino_prima/projects/prima1/__init__.py
lino_prima/projects/prima1/compute_sums.py
lino_prima/projects/prima1/initdb_csv2db.sh
lino_prima/projects/prima1/manage.py
lino_prima/projects/prima1/settings.py
lino_prima/projects/prima1/config/weasyprint/header.png
lino_prima/projects/prima1/fixtures/__init__.py
lino_prima/projects/prima1/fixtures/demo.py
lino_prima/projects/prima1/fixtures/std.py
lino_prima-25.6.0.dist-info/METADATA
lino_prima-25.6.0.dist-info/WHEEL
lino_prima-25.6.0.dist-info/licenses/COPYING
lino_prima-25.6.0.dist-info/RECORD
